litecow_models/__init__.py
litecow_models/cli.py
litecow_models/model.py
litecow_models-0.1.0.dist-info/entry_points.txt
litecow_models-0.1.0.dist-info/WHEEL
litecow_models-0.1.0.dist-info/METADATA
litecow_models-0.1.0.dist-info/RECORD
